pyemb/__init__.py
pyemb/_utils.py
pyemb/datasets.py
pyemb/embedding.py
pyemb/hc.py
pyemb/plotting.py
pyemb/preprocessing.py
pyemb/simulation.py
pyemb/tools.py
pyemb-1.0.0a13.dist-info/METADATA
pyemb-1.0.0a13.dist-info/WHEEL
pyemb-1.0.0a13.dist-info/licenses/LICENSE
pyemb-1.0.0a13.dist-info/RECORD
